README.md
pyproject.toml
setup.py
easyagents/__init__.py
easyagents/agents.py
easyagents/agents_test.py
easyagents/core.py
easyagents/core_test.py
easyagents/env.py
easyagents/env_test.py
easyagents.egg-info/PKG-INFO
easyagents.egg-info/SOURCES.txt
easyagents.egg-info/dependency_links.txt
easyagents.egg-info/entry_points.txt
easyagents.egg-info/requires.txt
easyagents.egg-info/top_level.txt
easyagents/backends/core.py
easyagents/backends/core_test.py
easyagents/backends/debug.py
easyagents/backends/default.py
easyagents/backends/monitor.py
easyagents/backends/monitor_test.py
easyagents/backends/tfagents.py
easyagents/backends/tfagents_test.py
easyagents/backends/tforce.py
easyagents/backends/tforce_test.py
easyagents/callbacks/duration.py
easyagents/callbacks/duration_test.py
easyagents/callbacks/log.py
easyagents/callbacks/log_test.py
easyagents/callbacks/plot.py
easyagents/callbacks/plot_test.py
easyagents/callbacks/save.py
easyagents/callbacks/save_test.py