Metadata-Version: 2.1
Name: easyagents
Version: 1.4.1
Summary: reinforcement learning for practitioners.
Home-page: https://github.com/christianhidber/easyagents
Author: Christian Hidber, Oliver Zeigermann
Author-email: christian.hidber@bsquare.ch
License: MIT
Platform: UNKNOWN
Classifier: License :: OSI Approved :: MIT License
Classifier: Programming Language :: Python :: 3
Classifier: Programming Language :: Python :: 3.7
